kube_agent/__init__.py
kube_agent/agent.py
kube_agent/cli.py
kube_agent/kubeconfig.py
kube_agent/prompts.py
kube_agent/shell.py
kube_agent/swarm/LICENSE
kube_agent/swarm/README.md
kube_agent/swarm/__init__.py
kube_agent/swarm/core.py
kube_agent/swarm/repl/__init__.py
kube_agent/swarm/repl/repl.py
kube_agent/swarm/types.py
kube_agent/swarm/util.py
kube_agent-0.2.0.dist-info/LICENSE
kube_agent-0.2.0.dist-info/METADATA
kube_agent-0.2.0.dist-info/WHEEL
kube_agent-0.2.0.dist-info/entry_points.txt
kube_agent-0.2.0.dist-info/RECORD
