Metadata-Version: 2.1
Name: kube-agent
Version: 0.2.0
Summary: A Kubernetes copilot agent powered by OpenAI
Home-page: https://github.com/feiskyer/kube-agent
Keywords: kubernetes,copilot,openai,chatgpt,agent,ai,agentic
Author: Pengfei Ni
Author-email: feiskyer@gmail.com
Requires-Python: >=3.10,<4.0
Classifier: Programming Language :: Python :: 3
Classifier: Programming Language :: Python :: 3.10
Classifier: Programming Language :: Python :: 3.11
Classifier: Programming Language :: Python :: 3.12
Classifier: Programming Language :: Python :: 3.13
Requires-Dist: click (>=8.1.7,<9.0.0)
Requires-Dist: kubernetes (>=31.0.0)
Requires-Dist: numpy (>=2.1.3,<3.0.0)
Requires-Dist: openai (>=1.54.4,<2.0.0)
Requires-Dist: python-dotenv (>=1.0.1,<2.0.0)
Requires-Dist: requests (>=2.32.3,<3.0.0)
Requires-Dist: tiktoken (>=0.8,<0.9)
Project-URL: Repository, https://github.com/feiskyer/kube-agent
